openHySim/OpenSees.exe
openHySim/Pnpscr64.dll
openHySim/__init__.py
openHySim/libcrypto-3-x64.dll
openHySim/libssl-3-x64.dll
openHySim/ntpciscr64.dll
openHySim/opensees.pyd
openHySim/xpcapi.dll
openHySim/lib/tcl8.6/init.tcl
openHySim/rthstools/simulink/scgt/virtualexperiment1/1dof/v1_1dof/ATS_setup.m
openHySim/rthstools/simulink/scgt/virtualexperiment1/1dof/v1_1dof/initializeSCRAMNetGT.m
openHySim/rthstools/simulink/scgt/virtualexperiment1/1dof/v1_1dof/initializeSimulation.m
openHySim/rthstools/simulink/scgt/virtualexperiment1/1dof/v1_1dof/v1_1dof_2020a.slx
openHySim/rthstools/simulink/scgt/virtualexperiment1/1dof/v1_1dof_initialize/initializeSCRAMNetGT.m
openHySim/rthstools/simulink/scgt/virtualexperiment1/1dof/v1_1dof_initialize/initializeSimulation.m
openHySim/rthstools/simulink/scgt/virtualexperiment1/1dof/v1_1dof_initialize/v1_1dof_initialize_2020a.slx
openHySim-0.0.8.dist-info/LICENSE.md
openHySim-0.0.8.dist-info/METADATA
openHySim-0.0.8.dist-info/WHEEL
openHySim-0.0.8.dist-info/top_level.txt
openHySim-0.0.8.dist-info/RECORD
