Metadata-Version: 2.1
Name: openHySim
Version: 0.0.8
Summary: A package contains OpenSeesPy 3.6.0, OpenFrescoPy 2.7.2, and personal subroutines
Home-page: http://github.com/nealleehit/osfeo
Author: Ning Li
Author-email: Ning Li <neallee@tju.edu.cn>
Project-URL: Homepage, https://github.com/nealleehit/osfeo
Project-URL: Bug Tracker, https://github.com/nealleehit/osfeo/issues
Classifier: Programming Language :: Python :: 3
Classifier: License :: OSI Approved :: MIT License
Classifier: Operating System :: Microsoft :: Windows
Requires-Python: >=3.11
License-File: LICENSE.md
